{
  "type": "ftbic:compressing",
  "conditions": [
    {
      "type": "forge:mod_loaded",
      "modid": "ftbic"
    },
    {
      "type": "gtexperimental:selected_profile",
      "properties": {
        "layout": "classic"
      }
    },
    {
      "type": "forge:mod_loaded",
      "modid": "ic2"
    }
  ],
  "inputItems": [
    {
      "count": 8,
      "ingredient": {
        "item": "minecraft:cactus"
      }
    }
  ],
  "outputItems": [
    {
      "item": "ic2:compressed_plants"
    }
  ]
}