{
  "type": "gtexperimental:industrial_electrolyzer",
  "conditions": [
    {
      "type": "forge:mod_loaded",
      "modid": "ic2"
    }
  ],
  "duration": 40,
  "energy_cost": 100.0,
  "input": {
    "type": "fluid",
    "amount": 7000,
    "tag": "forge:sulfuric_acid"
  },
  "output": [
    {
      "amount": 2000,
      "fluid": "gtexperimental:hydrogen_fluid"
    },
    {
      "amount": 1000,
      "fluid": "gtexperimental:sulfur_fluid"
    },
    {
      "amount": 2000,
      "fluid": "ic2:air"
    }
  ]
}